lvmc/__init__.py
lvmc/core/__init__.py
lvmc/core/magnetic_field.py
lvmc/core/particle_lattice.py
lvmc/core/simulation.py
lvmc/data_handling/__init__.py
lvmc/data_handling/data_collector.py
lvmc/data_handling/data_exporter.py
lvmc/data_handling/visualization.py
tests/__init__.py
lvmc-0.1.dist-info/LICENSE
lvmc-0.1.dist-info/METADATA
lvmc-0.1.dist-info/WHEEL
lvmc-0.1.dist-info/top_level.txt
lvmc-0.1.dist-info/RECORD
